Metadata-Version: 2.1
Name: openwithida
Version: 1.0.0
Summary: Right click -> "Open with IDA"
Home-page: https://github.com/ramikg/openwithida
License: UNKNOWN
Platform: UNKNOWN
Classifier: Programming Language :: Python :: 2
Classifier: Programming Language :: Python :: 3
Classifier: Operating System :: Microsoft :: Windows
License-File: LICENSE
